evergreenfft/_evergreen_fft.so
evergreenfft/evergreen_fft.py
evergreenfft-1.0.2.dist-info/LICENSE
evergreenfft-1.0.2.dist-info/METADATA
evergreenfft-1.0.2.dist-info/WHEEL
evergreenfft-1.0.2.dist-info/top_level.txt
evergreenfft-1.0.2.dist-info/RECORD
