Metadata-Version: 2.1
Name: evergreenfft
Version: 1.0.2
Summary: A python fft package based on evergreenforest
Home-page: https://github.com/SeanSRice/evergreen_fft.git
Author: Rice
Author-email: mrseanrice@gmail.com
License: UNKNOWN
Platform: UNKNOWN
Classifier: Programming Language :: Python :: 2.7
Classifier: License :: OSI Approved :: MIT License
